gofigure/__init__.py
gofigure/exceptions.py
gofigure/core/__init__.py
gofigure/core/base.py
gofigure-0.2.5.dist-info/METADATA
gofigure-0.2.5.dist-info/WHEEL
gofigure-0.2.5.dist-info/RECORD
