Metadata-Version: 2.4
Name: gofigure
Version: 0.2.5
Summary: Dynamic Attributable Config System
Project-URL: Homepage, https://github.com/schizoprada/gofigure
Project-URL: Repository, https://github.com/schizoprada/gofigure
Project-URL: Bug Tracker, https://github.com/schizoprada/gofigure/issues
Project-URL: Changelog, https://github.com/schizoprada/gofigure/blob/main/docs/CHANGELOG.md
Author-email: Joel Yisrael <schizoprada@gmail.com>
Maintainer-email: Joel Yisrael <schizoprada@gmail.com>
License: MIT
Keywords: attribute,config,configuration,dict,dynamic,json,persistence,settings,yaml
Classifier: Development Status :: 3 - Alpha
Classifier: Intended Audience :: Developers
Classifier: License :: OSI Approved :: MIT License
Classifier: Operating System :: OS Independent
Classifier: Programming Language :: Python :: 3
Classifier: Programming Language :: Python :: 3.9
Classifier: Programming Language :: Python :: 3.10
Classifier: Programming Language :: Python :: 3.11
Classifier: Programming Language :: Python :: 3.12
Classifier: Topic :: Internet :: WWW/HTTP :: Dynamic Content
Classifier: Topic :: Software Development :: Libraries :: Python Modules
Classifier: Topic :: Text Processing
Classifier: Topic :: Utilities
Requires-Python: >=3.9
Requires-Dist: pyyaml>=6.0.0
Provides-Extra: dev
Requires-Dist: black>=23.0.0; extra == 'dev'
Requires-Dist: flake8>=6.0.0; extra == 'dev'
Requires-Dist: isort>=5.12.0; extra == 'dev'
Requires-Dist: mypy>=1.0.0; extra == 'dev'
Requires-Dist: pre-commit>=3.0.0; extra == 'dev'
Requires-Dist: pytest-cov>=4.0.0; extra == 'dev'
Requires-Dist: pytest>=7.0.0; extra == 'dev'
Provides-Extra: docs
Requires-Dist: mkdocs-material>=9.0.0; extra == 'docs'
Requires-Dist: mkdocs>=1.5.0; extra == 'docs'
Requires-Dist: mkdocstrings[python]>=0.22.0; extra == 'docs'
Provides-Extra: test
Requires-Dist: pytest-cov>=4.0.0; extra == 'test'
Requires-Dist: pytest-xdist>=3.0.0; extra == 'test'
Requires-Dist: pytest>=7.0.0; extra == 'test'
